py.typed
cogroo4py/__init__.py
cogroo4py/cogroo.py
cogroo4py/generate_stubs.py
cogroo4py/jpype_config.py
cogroo4py/jars/Cogroo4PyBridge.jar
cogroo4py/jars/original-Cogroo4PyBridge.jar
cogroo_interface/__init__.py
java-stubs/__init__.pyi
java-stubs/util/__init__.pyi
java-stubs/util/concurrent/__init__.pyi
java-stubs/util/concurrent/atomic/__init__.pyi
java-stubs/util/concurrent/locks/__init__.pyi
java-stubs/util/function/__init__.pyi
java-stubs/util/jar/__init__.pyi
java-stubs/util/logging/__init__.pyi
java-stubs/util/prefs/__init__.pyi
java-stubs/util/regex/__init__.pyi
java-stubs/util/spi/__init__.pyi
java-stubs/util/stream/__init__.pyi
java-stubs/util/zip/__init__.pyi
jpype-stubs/__init__.pyi
jpype-stubs/py.typed
org-stubs/__init__.pyi
org-stubs/cogroo/__init__.pyi
org-stubs/cogroo/analyzer/__init__.pyi
org-stubs/cogroo/checker/__init__.pyi
org-stubs/cogroo/cmdline/__init__.pyi
org-stubs/cogroo/cmdline/chunker2/__init__.pyi
org-stubs/cogroo/cmdline/dictionary/__init__.pyi
org-stubs/cogroo/cmdline/featurizer/__init__.pyi
org-stubs/cogroo/config/__init__.pyi
org-stubs/cogroo/dictionary/__init__.pyi
org-stubs/cogroo/dictionary/impl/__init__.pyi
org-stubs/cogroo/entities/__init__.pyi
org-stubs/cogroo/entities/impl/__init__.pyi
org-stubs/cogroo/entities/tree/__init__.pyi
org-stubs/cogroo/errorreport/__init__.pyi
org-stubs/cogroo/exceptions/__init__.pyi
org-stubs/cogroo/formats/__init__.pyi
org-stubs/cogroo/formats/ad/__init__.pyi
org-stubs/cogroo/gc/__init__.pyi
org-stubs/cogroo/gc/cmdline/__init__.pyi
org-stubs/cogroo/gc/cmdline/dictionary/__init__.pyi
org-stubs/cogroo/gc/cmdline/grammarchecker/__init__.pyi
org-stubs/cogroo/interpreters/__init__.pyi
org-stubs/cogroo/text/__init__.pyi
org-stubs/cogroo/text/impl/__init__.pyi
org-stubs/cogroo/text/tree/__init__.pyi
org-stubs/cogroo/tools/__init__.pyi
org-stubs/cogroo/tools/checker/__init__.pyi
org-stubs/cogroo/tools/checker/checkers/__init__.pyi
org-stubs/cogroo/tools/checker/rules/__init__.pyi
cogroo4py-0.5.1.dist-info/METADATA
cogroo4py-0.5.1.dist-info/WHEEL
cogroo4py-0.5.1.dist-info/top_level.txt
cogroo4py-0.5.1.dist-info/RECORD
